amcrest/Makefile.am
amcrest/__init__.py
amcrest/audio.py
amcrest/config.py
amcrest/event.py
amcrest/exceptions.py
amcrest/http.py
amcrest/log.py
amcrest/media.py
amcrest/motion_detection.py
amcrest/nas.py
amcrest/network.py
amcrest/privacy_mode.py
amcrest/ptz.py
amcrest/py.typed
amcrest/record.py
amcrest/snapshot.py
amcrest/special.py
amcrest/storage.py
amcrest/system.py
amcrest/user_management.py
amcrest/utils.py
amcrest/video.py
amcrest-1.9.8.data/scripts/amcrest-cli
amcrest-1.9.8.data/scripts/amcrest-tui
amcrest-1.9.8.dist-info/AUTHORS
amcrest-1.9.8.dist-info/COPYING
amcrest-1.9.8.dist-info/METADATA
amcrest-1.9.8.dist-info/WHEEL
amcrest-1.9.8.dist-info/top_level.txt
amcrest-1.9.8.dist-info/zip-safe
amcrest-1.9.8.dist-info/RECORD
