Metadata-Version: 2.1
Name: amcrest
Version: 1.9.8
Summary: Python wrapper implementation for Amcrest cameras.
Home-page: http://github.com/tchellomello/python-amcrest
Author: Douglas Schilling Landgraf, Marcelo Moreira de Mello
Author-email: dougsland@gmail.com, tchello.mello@gmail.com
License: GPLv2
Keywords: amcrest camera python
Classifier: Programming Language :: Python
Classifier: Programming Language :: Python :: 3.7
Classifier: Programming Language :: Python :: 3.8
Classifier: Programming Language :: Python :: 3.9
Classifier: Programming Language :: Python :: 3.10
License-File: COPYING
License-File: AUTHORS
Requires-Dist: argcomplete
Requires-Dist: httpx
Requires-Dist: requests
Requires-Dist: typing-extensions
Requires-Dist: urllib3
